ai_agent_rules-0.19.2.dist-info/licenses/LICENSE
ai_rules/__init__.py
ai_rules/cli.py
ai_rules/completions.py
ai_rules/config.py
ai_rules/mcp.py
ai_rules/plugins.py
ai_rules/profiles.py
ai_rules/state.py
ai_rules/symlinks.py
ai_rules/utils.py
ai_rules/agents/__init__.py
ai_rules/agents/base.py
ai_rules/agents/claude.py
ai_rules/agents/goose.py
ai_rules/agents/shared.py
ai_rules/bootstrap/__init__.py
ai_rules/bootstrap/config.py
ai_rules/bootstrap/installer.py
ai_rules/bootstrap/updater.py
ai_rules/bootstrap/version.py
ai_rules/config/AGENTS.md
ai_rules/config/chat_agent_hints.md
ai_rules/config/claude/CLAUDE.md
ai_rules/config/claude/mcps.json
ai_rules/config/claude/settings.json
ai_rules/config/claude/agents/code-reviewer.md
ai_rules/config/claude/commands/agents-md.md
ai_rules/config/claude/commands/annotate-changelog.md
ai_rules/config/claude/commands/comment-cleanup.md
ai_rules/config/claude/commands/continue-crash.md
ai_rules/config/claude/commands/dev-docs.md
ai_rules/config/claude/commands/pr-creator.md
ai_rules/config/claude/commands/prompt-critique.md
ai_rules/config/claude/commands/refresh-plan.md
ai_rules/config/claude/commands/test-cleanup.md
ai_rules/config/claude/commands/update-docs.md
ai_rules/config/claude/hooks/skillRouter.py
ai_rules/config/claude/hooks/subagentStop.py
ai_rules/config/claude/skills/doc-writer/SKILL.md
ai_rules/config/claude/skills/doc-writer/resources/templates.md
ai_rules/config/claude/skills/prompt-engineer/SKILL.md
ai_rules/config/claude/skills/prompt-engineer/resources/prompt_engineering_guide_2025.md
ai_rules/config/claude/skills/prompt-engineer/resources/templates.md
ai_rules/config/goose/.goosehints
ai_rules/config/goose/config.yaml
ai_rules/config/profiles/default.yaml
ai_rules/config/profiles/work.yaml
ai_agent_rules-0.19.2.dist-info/METADATA
ai_agent_rules-0.19.2.dist-info/WHEEL
ai_agent_rules-0.19.2.dist-info/entry_points.txt
ai_agent_rules-0.19.2.dist-info/top_level.txt
ai_agent_rules-0.19.2.dist-info/RECORD
