Metadata-Version: 2.4
Name: ai-agent-rules
Version: 0.19.2
Summary: Manage user-level AI agent configurations
Author-email: Will Pfleger <pfleger.will@gmail.com>
License-Expression: MIT
Project-URL: Homepage, https://github.com/willpfleger/ai-rules
Project-URL: Repository, https://github.com/willpfleger/ai-rules
Project-URL: Issues, https://github.com/willpfleger/ai-rules/issues
Keywords: ai,cli,configuration,claude,goose,llm,agent
Classifier: Development Status :: 4 - Beta
Classifier: Environment :: Console
Classifier: Intended Audience :: Developers
Classifier: Programming Language :: Python :: 3
Classifier: Programming Language :: Python :: 3.10
Classifier: Programming Language :: Python :: 3.11
Classifier: Programming Language :: Python :: 3.12
Classifier: Programming Language :: Python :: 3.13
Classifier: Topic :: Software Development :: Libraries :: Python Modules
Classifier: Topic :: Utilities
Requires-Python: >=3.10
License-File: LICENSE
Requires-Dist: click>=8.1
Requires-Dist: hatch>=1.15.1
Requires-Dist: packaging>=21.0
Requires-Dist: pytest>=8.4.2
Requires-Dist: pytest-cov>=7.0.0
Requires-Dist: pytest-xdist>=3.8.0
Requires-Dist: pyyaml>=6.0
Requires-Dist: rich>=13.0
Requires-Dist: ruff>=0.14.3
Requires-Dist: tomli>=2.0.0; python_version < "3.11"
Dynamic: license-file
